README.md
setup.py
cloud_ml_common/__init__.py
cloud_ml_common.egg-info/PKG-INFO
cloud_ml_common.egg-info/SOURCES.txt
cloud_ml_common.egg-info/dependency_links.txt
cloud_ml_common.egg-info/requires.txt
cloud_ml_common.egg-info/top_level.txt
cloud_ml_common/auth/__init__.py
cloud_ml_common/auth/constant.py
cloud_ml_common/auth/signature.py
cloud_ml_common/auth/signature_test.py