Metadata-Version: 1.0
Name: cloud-ml-common
Version: 0.0.2
Summary: Xiaomi Cloud-ml Common
Home-page: UNKNOWN
Author: Xiaomi
Author-email: UNKNOWN
License: Apache License
Platform: UNKNOWN
